novelcraft/__init__.py
novelcraft/sdk/__init__.py
novelcraft/sdk/agent.py
novelcraft/sdk/block.py
novelcraft/sdk/block_source.py
novelcraft/sdk/client.py
novelcraft/sdk/entity.py
novelcraft/sdk/entity_source.py
novelcraft/sdk/inventory.py
novelcraft/sdk/item_stack.py
novelcraft/sdk/logger.py
novelcraft/sdk/message.py
novelcraft/sdk/orientation.py
novelcraft/sdk/position.py
novelcraft/sdk/sdk.py
novelcraft/sdk/section.py
novelcraft_sdk-0.2.0.dist-info/LICENSE
novelcraft_sdk-0.2.0.dist-info/METADATA
novelcraft_sdk-0.2.0.dist-info/WHEEL
novelcraft_sdk-0.2.0.dist-info/RECORD
