Metadata-Version: 2.1
Name: novelcraft-sdk
Version: 0.2.0
Summary: A Python library for communicating with NovelCraft Servers and accessing NovelCraft game data
License: Unlicense
Author: NovelCraft
Requires-Python: >=3.8,<4.0
Classifier: License :: Other/Proprietary License
Classifier: Programming Language :: Python :: 3
Classifier: Programming Language :: Python :: 3.8
Classifier: Programming Language :: Python :: 3.9
Classifier: Programming Language :: Python :: 3.10
Classifier: Programming Language :: Python :: 3.11
Requires-Dist: jsonschema (>=4.17.3,<5.0.0)
Requires-Dist: termcolor (>=2.2.0,<3.0.0)
Requires-Dist: websockets (>=10.4,<11.0)
